{
  "namespaces": [
    "public"
  ],
  "name": "public",
  "tables": [
    {
      "columns": {
        "id": {
          "name": "id",
          "type": "text",
          "unsigned": false,
          "autoincrement": false,
          "primary": true,
          "nullable": false,
          "unique": false,
          "length": null,
          "precision": null,
          "scale": null,
          "default": null,
          "comment": null,
          "enumItems": [],
          "mappedType": "text"
        },
        "title": {
          "name": "title",
          "type": "text",
          "unsigned": false,
          "autoincrement": false,
          "primary": false,
          "nullable": false,
          "unique": false,
          "length": null,
          "precision": null,
          "scale": null,
          "default": null,
          "comment": null,
          "enumItems": [],
          "mappedType": "text"
        },
        "type": {
          "name": "type",
          "type": "text",
          "unsigned": false,
          "autoincrement": false,
          "primary": false,
          "nullable": false,
          "unique": false,
          "length": null,
          "precision": null,
          "scale": null,
          "default": null,
          "comment": null,
          "enumItems": [
            "hero_carousel",
            "featured_categories",
            "product_showcase"
          ],
          "mappedType": "enum"
        },
        "layout": {
          "name": "layout",
          "type": "text",
          "unsigned": false,
          "autoincrement": false,
          "primary": false,
          "nullable": false,
          "unique": false,
          "length": null,
          "precision": null,
          "scale": null,
          "default": null,
          "comment": null,
          "enumItems": [],
          "mappedType": "text"
        },
        "position": {
          "name": "position",
          "type": "integer",
          "unsigned": false,
          "autoincrement": false,
          "primary": false,
          "nullable": false,
          "unique": false,
          "length": null,
          "precision": null,
          "scale": null,
          "default": null,
          "comment": null,
          "enumItems": [],
          "mappedType": "integer"
        },
        "enabled": {
          "name": "enabled",
          "type": "boolean",
          "unsigned": false,
          "autoincrement": false,
          "primary": false,
          "nullable": false,
          "unique": false,
          "length": null,
          "precision": null,
          "scale": null,
          "default": "true",
          "comment": null,
          "enumItems": [],
          "mappedType": "boolean"
        },
        "settings": {
          "name": "settings",
          "type": "jsonb",
          "unsigned": false,
          "autoincrement": false,
          "primary": false,
          "nullable": true,
          "unique": false,
          "length": null,
          "precision": null,
          "scale": null,
          "default": null,
          "comment": null,
          "enumItems": [],
          "mappedType": "json"
        },
        "created_at": {
          "name": "created_at",
          "type": "timestamptz",
          "unsigned": false,
          "autoincrement": false,
          "primary": false,
          "nullable": false,
          "unique": false,
          "length": 6,
          "precision": null,
          "scale": null,
          "default": "now()",
          "comment": null,
          "enumItems": [],
          "mappedType": "datetime"
        },
        "updated_at": {
          "name": "updated_at",
          "type": "timestamptz",
          "unsigned": false,
          "autoincrement": false,
          "primary": false,
          "nullable": false,
          "unique": false,
          "length": 6,
          "precision": null,
          "scale": null,
          "default": "now()",
          "comment": null,
          "enumItems": [],
          "mappedType": "datetime"
        },
        "deleted_at": {
          "name": "deleted_at",
          "type": "timestamptz",
          "unsigned": false,
          "autoincrement": false,
          "primary": false,
          "nullable": true,
          "unique": false,
          "length": 6,
          "precision": null,
          "scale": null,
          "default": null,
          "comment": null,
          "enumItems": [],
          "mappedType": "datetime"
        }
      },
      "name": "home_section",
      "schema": "public",
      "indexes": [
        {
          "keyName": "IDX_home_section_deleted_at",
          "columnNames": [],
          "composite": false,
          "constraint": false,
          "primary": false,
          "unique": false,
          "expression": "CREATE INDEX IF NOT EXISTS \"IDX_home_section_deleted_at\" ON \"home_section\" (\"deleted_at\") WHERE deleted_at IS NULL"
        },
        {
          "keyName": "home_section_pkey",
          "columnNames": [
            "id"
          ],
          "composite": false,
          "constraint": true,
          "primary": true,
          "unique": true
        }
      ],
      "checks": [],
      "foreignKeys": {},
      "nativeEnums": {}
    },
    {
      "columns": {
        "id": {
          "name": "id",
          "type": "text",
          "unsigned": false,
          "autoincrement": false,
          "primary": true,
          "nullable": false,
          "unique": false,
          "length": null,
          "precision": null,
          "scale": null,
          "default": null,
          "comment": null,
          "enumItems": [],
          "mappedType": "text"
        },
        "image_url": {
          "name": "image_url",
          "type": "text",
          "unsigned": false,
          "autoincrement": false,
          "primary": false,
          "nullable": false,
          "unique": false,
          "length": null,
          "precision": null,
          "scale": null,
          "default": null,
          "comment": null,
          "enumItems": [],
          "mappedType": "text"
        },
        "mobile_image_url": {
          "name": "mobile_image_url",
          "type": "text",
          "unsigned": false,
          "autoincrement": false,
          "primary": false,
          "nullable": true,
          "unique": false,
          "length": null,
          "precision": null,
          "scale": null,
          "default": null,
          "comment": null,
          "enumItems": [],
          "mappedType": "text"
        },
        "heading": {
          "name": "heading",
          "type": "text",
          "unsigned": false,
          "autoincrement": false,
          "primary": false,
          "nullable": true,
          "unique": false,
          "length": null,
          "precision": null,
          "scale": null,
          "default": null,
          "comment": null,
          "enumItems": [],
          "mappedType": "text"
        },
        "subheading": {
          "name": "subheading",
          "type": "text",
          "unsigned": false,
          "autoincrement": false,
          "primary": false,
          "nullable": true,
          "unique": false,
          "length": null,
          "precision": null,
          "scale": null,
          "default": null,
          "comment": null,
          "enumItems": [],
          "mappedType": "text"
        },
        "cta_label": {
          "name": "cta_label",
          "type": "text",
          "unsigned": false,
          "autoincrement": false,
          "primary": false,
          "nullable": true,
          "unique": false,
          "length": null,
          "precision": null,
          "scale": null,
          "default": null,
          "comment": null,
          "enumItems": [],
          "mappedType": "text"
        },
        "cta_link": {
          "name": "cta_link",
          "type": "text",
          "unsigned": false,
          "autoincrement": false,
          "primary": false,
          "nullable": true,
          "unique": false,
          "length": null,
          "precision": null,
          "scale": null,
          "default": null,
          "comment": null,
          "enumItems": [],
          "mappedType": "text"
        },
        "position": {
          "name": "position",
          "type": "integer",
          "unsigned": false,
          "autoincrement": false,
          "primary": false,
          "nullable": false,
          "unique": false,
          "length": null,
          "precision": null,
          "scale": null,
          "default": null,
          "comment": null,
          "enumItems": [],
          "mappedType": "integer"
        },
        "section_id": {
          "name": "section_id",
          "type": "text",
          "unsigned": false,
          "autoincrement": false,
          "primary": false,
          "nullable": false,
          "unique": false,
          "length": null,
          "precision": null,
          "scale": null,
          "default": null,
          "comment": null,
          "enumItems": [],
          "mappedType": "text"
        },
        "created_at": {
          "name": "created_at",
          "type": "timestamptz",
          "unsigned": false,
          "autoincrement": false,
          "primary": false,
          "nullable": false,
          "unique": false,
          "length": 6,
          "precision": null,
          "scale": null,
          "default": "now()",
          "comment": null,
          "enumItems": [],
          "mappedType": "datetime"
        },
        "updated_at": {
          "name": "updated_at",
          "type": "timestamptz",
          "unsigned": false,
          "autoincrement": false,
          "primary": false,
          "nullable": false,
          "unique": false,
          "length": 6,
          "precision": null,
          "scale": null,
          "default": "now()",
          "comment": null,
          "enumItems": [],
          "mappedType": "datetime"
        },
        "deleted_at": {
          "name": "deleted_at",
          "type": "timestamptz",
          "unsigned": false,
          "autoincrement": false,
          "primary": false,
          "nullable": true,
          "unique": false,
          "length": 6,
          "precision": null,
          "scale": null,
          "default": null,
          "comment": null,
          "enumItems": [],
          "mappedType": "datetime"
        }
      },
      "name": "home_slide",
      "schema": "public",
      "indexes": [
        {
          "keyName": "IDX_home_slide_section_id",
          "columnNames": [],
          "composite": false,
          "constraint": false,
          "primary": false,
          "unique": false,
          "expression": "CREATE INDEX IF NOT EXISTS \"IDX_home_slide_section_id\" ON \"home_slide\" (\"section_id\") WHERE deleted_at IS NULL"
        },
        {
          "keyName": "IDX_home_slide_deleted_at",
          "columnNames": [],
          "composite": false,
          "constraint": false,
          "primary": false,
          "unique": false,
          "expression": "CREATE INDEX IF NOT EXISTS \"IDX_home_slide_deleted_at\" ON \"home_slide\" (\"deleted_at\") WHERE deleted_at IS NULL"
        },
        {
          "keyName": "home_slide_pkey",
          "columnNames": [
            "id"
          ],
          "composite": false,
          "constraint": true,
          "primary": true,
          "unique": true
        }
      ],
      "checks": [],
      "foreignKeys": {
        "home_slide_section_id_foreign": {
          "constraintName": "home_slide_section_id_foreign",
          "columnNames": [
            "section_id"
          ],
          "localTableName": "public.home_slide",
          "referencedColumnNames": [
            "id"
          ],
          "referencedTableName": "public.home_section",
          "updateRule": "cascade"
        }
      },
      "nativeEnums": {}
    }
  ],
  "nativeEnums": {}
}
